agenters/__init__.py
agenters/aider_mcp_server.py
agenters/claude_mcp_server.py
agenters/codex_mcp_server.py
agenters/gemini_mcp_server.py
agenters/goose_mcp_server.py
agenters/manus_mcp_server.py
agenters-0.3.0.dist-info/METADATA
agenters-0.3.0.dist-info/WHEEL
agenters-0.3.0.dist-info/entry_points.txt
agenters-0.3.0.dist-info/top_level.txt
agenters-0.3.0.dist-info/RECORD
