Metadata-Version: 2.4
Name: agenters
Version: 0.3.0
Summary: MCP servers that allow AI agents to interact with various AI coding assistants
Author-email: Roei Bar <roei@example.com>
License-Expression: MIT
Project-URL: Homepage, https://github.com/roeiba/agenters
Project-URL: Bug Tracker, https://github.com/roeiba/agenters/issues
Classifier: Programming Language :: Python :: 3
Classifier: Operating System :: OS Independent
Requires-Python: >=3.10
Requires-Dist: mcp[cli]>=1.2.0
Requires-Dist: claude-agent-sdk>=0.1.0
